pytitler/__init__.py
pytitler/pytitler.py
pytitler-1.0.2.dist-info/LICENSE
pytitler-1.0.2.dist-info/METADATA
pytitler-1.0.2.dist-info/WHEEL
pytitler-1.0.2.dist-info/top_level.txt
pytitler-1.0.2.dist-info/RECORD
