Metadata-Version: 2.1
Name: pytitler
Version: 1.0.2
Summary: Easy printing titles
Author: Flowseal
Author-email: <alegiumselly@gmail.com>
Keywords: python,pystyle
Classifier: Programming Language :: Python :: 3
Classifier: Operating System :: Unix
Classifier: Operating System :: MacOS :: MacOS X
Classifier: Operating System :: Microsoft :: Windows
License-File: LICENSE
Requires-Dist: opencv-python
Requires-Dist: pyautogui
Requires-Dist: pyaudio
